i3blocks_mpris.py
i3blocks_mpris-2.3.0.dist-info/licenses/LICENSE
i3blocks_mpris-2.3.0.dist-info/METADATA
i3blocks_mpris-2.3.0.dist-info/WHEEL
i3blocks_mpris-2.3.0.dist-info/entry_points.txt
i3blocks_mpris-2.3.0.dist-info/top_level.txt
i3blocks_mpris-2.3.0.dist-info/zip-safe
i3blocks_mpris-2.3.0.dist-info/RECORD
