Metadata-Version: 2.4
Name: i3blocks-mpris
Version: 2.3.0
Summary: A persistent i3blocks blocklet for the MPRIS D-Bus interface
Author-email: Dmitry Meyer <me@undef.im>
License-Expression: MIT
Project-URL: Homepage, https://github.com/un-def/i3blocks-mpris
Project-URL: Repository, https://github.com/un-def/i3blocks-mpris.git
Project-URL: Changelog, https://github.com/un-def/i3blocks-mpris/blob/master/CHANGELOG.md
Project-URL: Issues, https://github.com/un-def/i3blocks-mpris/issues
Keywords: i3blocks,blocklet
Classifier: Development Status :: 5 - Production/Stable
Classifier: Intended Audience :: End Users/Desktop
Classifier: Operating System :: POSIX :: Linux
Classifier: Programming Language :: Python :: 3
Classifier: Programming Language :: Python :: 3.10
Classifier: Programming Language :: Python :: 3.11
Classifier: Programming Language :: Python :: 3.12
Classifier: Programming Language :: Python :: 3.13
Classifier: Programming Language :: Python :: 3.14
Requires-Python: >=3.10
License-File: LICENSE
Requires-Dist: dbus-python<1.5,>=1.3
Requires-Dist: PyGObject<3.55,>=3.54
Dynamic: license-file
